quantselect/__init__.py
quantselect/cli.py
quantselect/config.py
quantselect/constants.py
quantselect/dataloader.py
quantselect/directlfq.py
quantselect/evaluation.py
quantselect/featureengineering.py
quantselect/gui.py
quantselect/loader.py
quantselect/loss.py
quantselect/manuscript_plotting_helper.py
quantselect/ms1_features.py
quantselect/output.py
quantselect/performance_evalution.py
quantselect/preprocessing.py
quantselect/shared_state.py
quantselect/simulation.py
quantselect/utils.py
quantselect/var_model.py
quantselect/visualizer.py
quantselect-0.1.0.dist-info/licenses/LICENSE
quantselect-0.1.0.dist-info/METADATA
quantselect-0.1.0.dist-info/WHEEL
quantselect-0.1.0.dist-info/entry_points.txt
quantselect-0.1.0.dist-info/top_level.txt
quantselect-0.1.0.dist-info/RECORD
