Metadata-Version: 2.4
Name: quantselect
Version: 0.1.0
Summary: An open-source Python package of the AlphaPept ecosystem
Author-email: Mann Labs <opensource@alphapept.com>
License: Apache
Project-URL: Homepage, https://github.com/MannLabs/quantselect
Project-URL: Mann Labs at MPIB, https://www.biochem.mpg.de/mann
Project-URL: Mann Labs at CPR, https://www.cpr.ku.dk/research/proteomics/mann/
Project-URL: GitHub, https://github.com/MannLabs/quantselect
Project-URL: PyPI, https://pypi.org/project/quantselect/
Keywords: bioinformatics,software,AlphaPept ecosystem
Classifier: Development Status :: 3 - Alpha
Classifier: Intended Audience :: Science/Research
Classifier: License :: OSI Approved :: Apache Software License
Classifier: Operating System :: OS Independent
Classifier: Programming Language :: Python :: 3
Classifier: Programming Language :: Python :: 3.9
Classifier: Programming Language :: Python :: 3.10
Classifier: Programming Language :: Python :: 3.11
Classifier: Topic :: Scientific/Engineering :: Bio-Informatics
Requires-Python: >=3.9
License-File: LICENSE
Requires-Dist: numpy>=1.26.0
Requires-Dist: pandas>=2.1.0
Requires-Dist: scipy>=1.12.0
Requires-Dist: pyteomics>=4.6.0
Requires-Dist: h5py>=3.10.0
Requires-Dist: alpharaw>=0.4.0
Requires-Dist: directlfq>=0.3.0
Requires-Dist: numba
Requires-Dist: joblib>=1.3.0
Requires-Dist: matplotlib>=3.8.0
Requires-Dist: seaborn>=0.13.0
Requires-Dist: plotly>=5.18.0
Requires-Dist: click>=8.0.1
Requires-Dist: tqdm>=4.66.0
Requires-Dist: pyarrow>=20.0.0
Requires-Dist: openpyxl>=3.1.0
Requires-Dist: scikit-learn>=1.3.0
Requires-Dist: torch>=2.2.0
Requires-Dist: pyyaml>=6.0.0
Provides-Extra: development
Requires-Dist: pytest>=7.4.0; extra == "development"
Requires-Dist: pytest-cov>=4.0.0; extra == "development"
Requires-Dist: ruff>=0.11.0; extra == "development"
Requires-Dist: pre-commit>=3.8.0; extra == "development"
Requires-Dist: sphinx>=5.3.0; extra == "development"
Requires-Dist: sphinx-rtd-theme>=1.2.0; extra == "development"
Requires-Dist: bump-my-version>=0.10.0; extra == "development"
Requires-Dist: build>=1.3.0; extra == "development"
Requires-Dist: twine>=4.0.0; extra == "development"
Requires-Dist: jupyter>=1.0.0; extra == "development"
Requires-Dist: ipykernel>=6.20.0; extra == "development"
Provides-Extra: stable
Requires-Dist: numpy==1.26.0; extra == "stable"
Requires-Dist: pandas==2.1.0; extra == "stable"
Requires-Dist: scipy==1.12.0; extra == "stable"
Requires-Dist: pyteomics==4.6.0; extra == "stable"
Requires-Dist: h5py==3.10.0; extra == "stable"
Requires-Dist: alpharaw==0.4.0; extra == "stable"
Requires-Dist: directlfq==0.3.0; extra == "stable"
Requires-Dist: numba; extra == "stable"
Requires-Dist: joblib==1.3.0; extra == "stable"
Requires-Dist: matplotlib==3.8.0; extra == "stable"
Requires-Dist: seaborn==0.13.0; extra == "stable"
Requires-Dist: plotly==5.18.0; extra == "stable"
Requires-Dist: click==8.0.1; extra == "stable"
Requires-Dist: tqdm==4.66.0; extra == "stable"
Requires-Dist: pyarrow==20.0.0; extra == "stable"
Requires-Dist: openpyxl==3.1.0; extra == "stable"
Requires-Dist: scikit-learn==1.3.0; extra == "stable"
Requires-Dist: torch==2.2.0; extra == "stable"
Requires-Dist: pyyaml==6.0.0; extra == "stable"
Dynamic: license-file
